__init__.py
create_folders.py
down_path.py
forganiser.py
header.py
move_files.py
forganiser-0.0.2.dist-info/LICENSE.txt
forganiser-0.0.2.dist-info/METADATA
forganiser-0.0.2.dist-info/WHEEL
forganiser-0.0.2.dist-info/entry_points.txt
forganiser-0.0.2.dist-info/top_level.txt
forganiser-0.0.2.dist-info/RECORD
