Metadata-Version: 2.1
Name: forganiser
Version: 0.0.2
Summary: A nifty tool to sort your messy folders
Home-page: https://github.com/cheesemaafia/forganiser
Author: Jigyasu
Author-email: jigyasu@outlook.in
License: UNKNOWN
Project-URL: Bug Tracker, https://github.com/cheesemaafia/forganiser/issues
Platform: UNKNOWN
Classifier: Programming Language :: Python :: 3
Classifier: License :: OSI Approved :: MIT License
Classifier: Operating System :: OS Independent
Requires-Python: >=3.6
License-File: LICENSE.txt
Requires-Dist: termcolor
